{
  "batch_size": 4,
  "max_model_len": 16384,
  "num_gpu_blocks_override": 319,
  "arrival_pattern": "LognormalArrival(lambda=0.0025568740575624468,cv=2,max=67792)",
  "vocab": [200, 30000],
  "peak_batch_blocks": 1384,
  "requests": {
    "request_0": {"category": "SSS_I96-144_O96-144", "input_length": 114, "output_length": 96, "arrival_time": 0, "sched_time": 0, "wait_time": 0},
    "request_1": {"category": "LMS_I3264-4912_O400-608", "input_length": 4804, "output_length": 586, "arrival_time": 210, "sched_time": 210, "wait_time": 0},
    "request_2": {"category": "SSS_I48-64_O48-64", "input_length": 53, "output_length": 64, "arrival_time": 1737, "sched_time": 1737, "wait_time": 0},
    "request_3": {"category": "MSS_I816-1216_O192-304", "input_length": 1070, "output_length": 213, "arrival_time": 1983, "sched_time": 1983, "wait_time": 0},
    "request_4": {"category": "MMS_I816-1216_O400-608", "input_length": 1181, "output_length": 463, "arrival_time": 2310, "sched_time": 2310, "wait_time": 0},
    "request_5": {"category": "MSS_I816-1216_O48-64", "input_length": 994, "output_length": 61, "arrival_time": 2464, "sched_time": 2464, "wait_time": 0},
    "request_6": {"category": "MSL_I816-1216_O3264-4912", "input_length": 1178, "output_length": 4596, "arrival_time": 2512, "sched_time": 2512, "wait_time": 0},
    "request_7": {"category": "MSL_I400-608_O1632-2448", "input_length": 560, "output_length": 1978, "arrival_time": 3241, "sched_time": 3241, "wait_time": 0},
    "request_8": {"category": "MSS_I400-608_O48-64", "input_length": 465, "output_length": 64, "arrival_time": 3353, "sched_time": 3353, "wait_time": 0},
    "request_9": {"category": "SSS_I48-64_O48-64", "input_length": 61, "output_length": 64, "arrival_time": 3513, "sched_time": 3513, "wait_time": 0},
    "request_10": {"category": "LSS_I1632-2448_O48-64", "input_length": 1961, "output_length": 54, "arrival_time": 3550, "sched_time": 3550, "wait_time": 0},
    "request_11": {"category": "SSL_I192-304_O3264-4912", "input_length": 296, "output_length": 4374, "arrival_time": 3745, "sched_time": 3745, "wait_time": 0},
    "request_12": {"category": "LSS_I3264-4912_O192-304", "input_length": 4680, "output_length": 213, "arrival_time": 4477, "sched_time": 7109, "wait_time": 2632},
    "request_13": {"category": "SMS_I192-304_O400-608", "input_length": 236, "output_length": 531, "arrival_time": 4614, "sched_time": 7323, "wait_time": 2709},
    "request_14": {"category": "SSS_I48-64_O192-304", "input_length": 57, "output_length": 265, "arrival_time": 4768, "sched_time": 7323, "wait_time": 2555},
    "request_15": {"category": "SSS_I48-64_O48-64", "input_length": 58, "output_length": 61, "arrival_time": 5212, "sched_time": 7323, "wait_time": 2111},
    "request_16": {"category": "SSL_I96-144_O1632-2448", "input_length": 100, "output_length": 2111, "arrival_time": 5394, "sched_time": 7385, "wait_time": 1991},
    "request_17": {"category": "SSL_I48-64_O3264-4912", "input_length": 62, "output_length": 4093, "arrival_time": 5706, "sched_time": 7589, "wait_time": 1883},
    "request_18": {"category": "SMS_I192-304_O816-1216", "input_length": 279, "output_length": 1133, "arrival_time": 5732, "sched_time": 7855, "wait_time": 2123},
    "request_19": {"category": "LMS_I3264-4912_O400-608", "input_length": 3420, "output_length": 408, "arrival_time": 5804, "sched_time": 8120, "wait_time": 2316},
    "request_20": {"category": "MSS_I816-1216_O48-64", "input_length": 1178, "output_length": 62, "arrival_time": 6202, "sched_time": 8529, "wait_time": 2327},
    "request_21": {"category": "SSL_I96-144_O1632-2448", "input_length": 109, "output_length": 1742, "arrival_time": 6234, "sched_time": 8592, "wait_time": 2358},
    "request_22": {"category": "LSS_I3264-4912_O96-144", "input_length": 4892, "output_length": 140, "arrival_time": 6676, "sched_time": 9497, "wait_time": 2821},
    "request_23": {"category": "SSL_I192-304_O1632-2448", "input_length": 301, "output_length": 2377, "arrival_time": 6984, "sched_time": 9638, "wait_time": 2654},
    "request_24": {"category": "LSS_I1632-2448_O48-64", "input_length": 2401, "output_length": 64, "arrival_time": 7226, "sched_time": 9638, "wait_time": 2412},
    "request_25": {"category": "MMS_I400-608_O816-1216", "input_length": 504, "output_length": 1049, "arrival_time": 7270, "sched_time": 9703, "wait_time": 2433},
    "request_26": {"category": "LMS_I1632-2448_O816-1216", "input_length": 2243, "output_length": 1008, "arrival_time": 7516, "sched_time": 10335, "wait_time": 2819},
    "request_27": {"category": "MSS_I400-608_O192-304", "input_length": 432, "output_length": 243, "arrival_time": 7701, "sched_time": 10753, "wait_time": 3052},
    "request_28": {"category": "LSS_I3264-4912_O96-144", "input_length": 3374, "output_length": 105, "arrival_time": 7778, "sched_time": 11344, "wait_time": 3566},
    "request_29": {"category": "MSS_I816-1216_O48-64", "input_length": 924, "output_length": 63, "arrival_time": 8213, "sched_time": 11344, "wait_time": 3131},
    "request_30": {"category": "MSL_I400-608_O1632-2448", "input_length": 435, "output_length": 2146, "arrival_time": 8641, "sched_time": 11408, "wait_time": 2767},
    "request_31": {"category": "MSL_I400-608_O3264-4912", "input_length": 587, "output_length": 4816, "arrival_time": 8701, "sched_time": 11450, "wait_time": 2749},
    "request_32": {"category": "MSL_I816-1216_O3264-4912", "input_length": 1112, "output_length": 4457, "arrival_time": 9221, "sched_time": 11683, "wait_time": 2462},
    "request_33": {"category": "SMS_I48-64_O816-1216", "input_length": 64, "output_length": 1163, "arrival_time": 9259, "sched_time": 12016, "wait_time": 2757},
    "request_34": {"category": "SSL_I192-304_O3264-4912", "input_length": 262, "output_length": 3457, "arrival_time": 9488, "sched_time": 13180, "wait_time": 3692},
    "request_35": {"category": "SSS_I96-144_O48-64", "input_length": 135, "output_length": 51, "arrival_time": 9581, "sched_time": 13555, "wait_time": 3974},
    "request_36": {"category": "MSS_I400-608_O192-304", "input_length": 518, "output_length": 267, "arrival_time": 10821, "sched_time": 13607, "wait_time": 2786},
    "request_37": {"category": "LMS_I3264-4912_O816-1216", "input_length": 4368, "output_length": 985, "arrival_time": 13901, "sched_time": 16267, "wait_time": 2366},
    "request_38": {"category": "MSL_I816-1216_O3264-4912", "input_length": 927, "output_length": 3911, "arrival_time": 13943, "sched_time": 17253, "wait_time": 3310},
    "request_39": {"category": "LSS_I1632-2448_O48-64", "input_length": 2302, "output_length": 55, "arrival_time": 14852, "sched_time": 17253, "wait_time": 2401},
    "request_40": {"category": "SSL_I192-304_O3264-4912", "input_length": 215, "output_length": 3462, "arrival_time": 15468, "sched_time": 17253, "wait_time": 1785},
    "request_41": {"category": "LSS_I3264-4912_O48-64", "input_length": 3309, "output_length": 53, "arrival_time": 15840, "sched_time": 17309, "wait_time": 1469},
    "request_42": {"category": "LMS_I1632-2448_O400-608", "input_length": 2057, "output_length": 606, "arrival_time": 16006, "sched_time": 17363, "wait_time": 1357},
    "request_43": {"category": "SSS_I96-144_O48-64", "input_length": 142, "output_length": 54, "arrival_time": 16166, "sched_time": 17363, "wait_time": 1197},
    "request_44": {"category": "LSS_I3264-4912_O192-304", "input_length": 4088, "output_length": 212, "arrival_time": 16344, "sched_time": 20716, "wait_time": 4372},
    "request_45": {"category": "MMS_I816-1216_O816-1216", "input_length": 1077, "output_length": 913, "arrival_time": 16372, "sched_time": 20929, "wait_time": 4557},
    "request_46": {"category": "MSL_I400-608_O3264-4912", "input_length": 466, "output_length": 3597, "arrival_time": 16544, "sched_time": 20929, "wait_time": 4385},
    "request_47": {"category": "LMS_I3264-4912_O816-1216", "input_length": 4308, "output_length": 1060, "arrival_time": 16597, "sched_time": 21843, "wait_time": 5246},
    "request_48": {"category": "SSS_I48-64_O48-64", "input_length": 59, "output_length": 52, "arrival_time": 17446, "sched_time": 21843, "wait_time": 4397},
    "request_49": {"category": "MMS_I816-1216_O816-1216", "input_length": 1157, "output_length": 874, "arrival_time": 18952, "sched_time": 22904, "wait_time": 3952},
    "request_50": {"category": "MSS_I816-1216_O96-144", "input_length": 927, "output_length": 134, "arrival_time": 19010, "sched_time": 22904, "wait_time": 3894},
    "request_51": {"category": "SMS_I96-144_O400-608", "input_length": 100, "output_length": 406, "arrival_time": 19146, "sched_time": 22904, "wait_time": 3758}
  }
}
