{
  "batch_size": 4,
  "max_model_len": 131072,
  "num_gpu_blocks_override": 2256,
  "arrival_pattern": "LognormalArrival(lambda=0.0003881623286327302,cv=1,max=306205)",
  "vocab": [200, 30000],
  "peak_batch_blocks": 9806,
  "requests": {
    "request_0": {"category": "SSL_I400-608_O16384-24576", "input_length": 500, "output_length": 18354, "arrival_time": 0, "sched_time": 0, "wait_time": 0},
    "request_1": {"category": "MSS_I13104-19648_O192-304", "input_length": 14088, "output_length": 223, "arrival_time": 3567, "sched_time": 3567, "wait_time": 0},
    "request_2": {"category": "LSS_I21296-31936_O192-304", "input_length": 29715, "output_length": 220, "arrival_time": 8444, "sched_time": 8444, "wait_time": 0},
    "request_3": {"category": "LSL_I13104-19648_O16384-24576", "input_length": 19404, "output_length": 19217, "arrival_time": 8889, "sched_time": 8889, "wait_time": 0},
    "request_4": {"category": "MSS_I6544-9824_O816-1216", "input_length": 9746, "output_length": 1006, "arrival_time": 11907, "sched_time": 11907, "wait_time": 0},
    "request_5": {"category": "LMS_I16384-24576_O4912-7360", "input_length": 18666, "output_length": 5861, "arrival_time": 14980, "sched_time": 28107, "wait_time": 13127},
    "request_6": {"category": "LMS_I13104-19648_O9824-14736", "input_length": 18240, "output_length": 11358, "arrival_time": 22957, "sched_time": 33969, "wait_time": 11012},
    "request_7": {"category": "SSL_I816-1216_O13104-19648", "input_length": 1183, "output_length": 18574, "arrival_time": 24285, "sched_time": 33969, "wait_time": 9684},
    "request_8": {"category": "LMS_I16384-24576_O9824-14736", "input_length": 19336, "output_length": 11571, "arrival_time": 25570, "sched_time": 45328, "wait_time": 19758},
    "request_9": {"category": "LSS_I21296-31936_O1632-2448", "input_length": 27385, "output_length": 2053, "arrival_time": 26049, "sched_time": 56900, "wait_time": 30851},
    "request_10": {"category": "LMS_I16384-24576_O4912-7360", "input_length": 22528, "output_length": 6303, "arrival_time": 26652, "sched_time": 58954, "wait_time": 32302},
    "request_11": {"category": "SSS_I400-608_O400-608", "input_length": 502, "output_length": 582, "arrival_time": 28479, "sched_time": 58954, "wait_time": 30475},
    "request_12": {"category": "LMS_I13104-19648_O9824-14736", "input_length": 13949, "output_length": 14065, "arrival_time": 29352, "sched_time": 65258, "wait_time": 35906},
    "request_13": {"category": "LSS_I19648-29488_O400-608", "input_length": 25886, "output_length": 549, "arrival_time": 33969, "sched_time": 79324, "wait_time": 45355},
    "request_14": {"category": "MSL_I3264-4912_O16384-24576", "input_length": 4385, "output_length": 20764, "arrival_time": 38317, "sched_time": 79324, "wait_time": 41007},
    "request_15": {"category": "LSS_I19648-29488_O400-608", "input_length": 26194, "output_length": 435, "arrival_time": 39981, "sched_time": 79874, "wait_time": 39893},
    "request_16": {"category": "LSS_I21296-31936_O816-1216", "input_length": 30926, "output_length": 910, "arrival_time": 41343, "sched_time": 80310, "wait_time": 38967},
    "request_17": {"category": "LSS_I21296-31936_O192-304", "input_length": 27804, "output_length": 197, "arrival_time": 42314, "sched_time": 81221, "wait_time": 38907},
    "request_18": {"category": "LMS_I19648-29488_O3264-4912", "input_length": 22095, "output_length": 3301, "arrival_time": 43276, "sched_time": 81419, "wait_time": 38143},
    "request_19": {"category": "LMS_I13104-19648_O4912-7360", "input_length": 14951, "output_length": 5380, "arrival_time": 43717, "sched_time": 84721, "wait_time": 41004},
    "request_20": {"category": "MSS_I3264-4912_O400-608", "input_length": 3635, "output_length": 536, "arrival_time": 44735, "sched_time": 84721, "wait_time": 39986},
    "request_21": {"category": "LMS_I16384-24576_O9824-14736", "input_length": 17514, "output_length": 13287, "arrival_time": 45242, "sched_time": 90102, "wait_time": 44860},
    "request_22": {"category": "LMS_I16384-24576_O6544-9824", "input_length": 18597, "output_length": 7220, "arrival_time": 48008, "sched_time": 103390, "wait_time": 55382},
    "request_23": {"category": "LSL_I16384-24576_O21296-31936", "input_length": 17059, "output_length": 29471, "arrival_time": 48821, "sched_time": 103390, "wait_time": 54569},
    "request_24": {"category": "LMS_I13104-19648_O13104-19648", "input_length": 14707, "output_length": 18622, "arrival_time": 49229, "sched_time": 110611, "wait_time": 61382},
    "request_25": {"category": "LSS_I19648-29488_O400-608", "input_length": 24133, "output_length": 419, "arrival_time": 51015, "sched_time": 132862, "wait_time": 81847},
    "request_26": {"category": "LMS_I13104-19648_O9824-14736", "input_length": 15010, "output_length": 13463, "arrival_time": 52122, "sched_time": 133282, "wait_time": 81160},
    "request_27": {"category": "LSS_I19648-29488_O816-1216", "input_length": 24430, "output_length": 852, "arrival_time": 52595, "sched_time": 146746, "wait_time": 94151},
    "request_28": {"category": "LSL_I16384-24576_O13104-19648", "input_length": 22501, "output_length": 14144, "arrival_time": 53491, "sched_time": 147599, "wait_time": 94108},
    "request_29": {"category": "LMS_I13104-19648_O9824-14736", "input_length": 13340, "output_length": 13511, "arrival_time": 54017, "sched_time": 147599, "wait_time": 93582},
    "request_30": {"category": "LMS_I13104-19648_O13104-19648", "input_length": 17893, "output_length": 15286, "arrival_time": 55222, "sched_time": 161744, "wait_time": 106522},
    "request_31": {"category": "SSL_I1632-2448_O21296-31936", "input_length": 2227, "output_length": 28463, "arrival_time": 57470, "sched_time": 161744, "wait_time": 104274},
    "request_32": {"category": "LSL_I19648-29488_O13104-19648", "input_length": 20786, "output_length": 14304, "arrival_time": 58597, "sched_time": 177031, "wait_time": 118434},
    "request_33": {"category": "LSS_I21296-31936_O1632-2448", "input_length": 23727, "output_length": 2372, "arrival_time": 63385, "sched_time": 191336, "wait_time": 127951},
    "request_34": {"category": "LSS_I16384-24576_O1632-2448", "input_length": 22112, "output_length": 2016, "arrival_time": 65383, "sched_time": 193709, "wait_time": 128326},
    "request_35": {"category": "MSL_I4912-7360_O21296-31936", "input_length": 5024, "output_length": 24471, "arrival_time": 66942, "sched_time": 193709, "wait_time": 126767},
    "request_36": {"category": "SSS_I400-608_O816-1216", "input_length": 580, "output_length": 1025, "arrival_time": 67739, "sched_time": 193709, "wait_time": 125970},
    "request_37": {"category": "LSS_I13104-19648_O192-304", "input_length": 17380, "output_length": 209, "arrival_time": 70313, "sched_time": 195726, "wait_time": 125413},
    "request_38": {"category": "SSL_I400-608_O16384-24576", "input_length": 453, "output_length": 18664, "arrival_time": 73765, "sched_time": 195726, "wait_time": 121961},
    "request_39": {"category": "LMS_I16384-24576_O4912-7360", "input_length": 21989, "output_length": 6483, "arrival_time": 74592, "sched_time": 195936, "wait_time": 121344},
    "request_40": {"category": "SSL_I816-1216_O21296-31936", "input_length": 1189, "output_length": 27174, "arrival_time": 76347, "sched_time": 195936, "wait_time": 119589},
    "request_41": {"category": "LMS_I13104-19648_O3264-4912", "input_length": 17748, "output_length": 3873, "arrival_time": 78321, "sched_time": 202420, "wait_time": 124099},
    "request_42": {"category": "LSS_I21296-31936_O192-304", "input_length": 31168, "output_length": 297, "arrival_time": 78906, "sched_time": 218181, "wait_time": 139275},
    "request_43": {"category": "LMS_I16384-24576_O9824-14736", "input_length": 22072, "output_length": 12521, "arrival_time": 79817, "sched_time": 218479, "wait_time": 138662},
    "request_44": {"category": "SSS_I192-304_O1632-2448", "input_length": 232, "output_length": 1638, "arrival_time": 83877, "sched_time": 218479, "wait_time": 134602},
    "request_45": {"category": "SSS_I400-608_O192-304", "input_length": 562, "output_length": 231, "arrival_time": 86400, "sched_time": 218479, "wait_time": 132079},
    "request_46": {"category": "MMS_I13104-19648_O13104-19648", "input_length": 18415, "output_length": 15391, "arrival_time": 89020, "sched_time": 231001, "wait_time": 141981},
    "request_47": {"category": "LMS_I16384-24576_O4912-7360", "input_length": 21071, "output_length": 6948, "arrival_time": 90644, "sched_time": 246393, "wait_time": 155749},
    "request_48": {"category": "SSS_I192-304_O400-608", "input_length": 242, "output_length": 574, "arrival_time": 92562, "sched_time": 246393, "wait_time": 153831},
    "request_49": {"category": "LMS_I13104-19648_O9824-14736", "input_length": 13283, "output_length": 12068, "arrival_time": 97682, "sched_time": 246393, "wait_time": 148711},
    "request_50": {"category": "SSL_I816-1216_O16384-24576", "input_length": 850, "output_length": 21436, "arrival_time": 98840, "sched_time": 246393, "wait_time": 147553},
    "request_51": {"category": "LSS_I21296-31936_O816-1216", "input_length": 22076, "output_length": 984, "arrival_time": 102642, "sched_time": 258462, "wait_time": 155820}
  }
}
